pyaiplayer/EnvironmentWrapper.py
pyaiplayer/__init__.py
pyaiplayer/demo_human_vs_ai.py
pyaiplayer/main.py
pyaiplayer-0.1.3.dist-info/LICENSE
pyaiplayer-0.1.3.dist-info/METADATA
pyaiplayer-0.1.3.dist-info/WHEEL
pyaiplayer-0.1.3.dist-info/top_level.txt
pyaiplayer-0.1.3.dist-info/RECORD
