Metadata-Version: 2.1
Name: pyaiplayer
Version: 0.1.3
Summary: A tool to let human play game against AI model
License-File: LICENSE
Requires-Dist: setuptools (~=65.0.0)
Requires-Dist: gym (~=0.21.0)
Requires-Dist: numpy (~=1.24.4)
Requires-Dist: matplotlib (~=3.2.2)
Requires-Dist: keyboard (~=0.13.5)
Requires-Dist: gym-retro (==0.8.0)
Requires-Dist: stable-baselines3 (==1.7.0)
Requires-Dist: tensorboard (==2.12.1)
